cvs/__init__.py
cvs/command_line.py
cvs/default.py
cvs/generate.py
cvs/initialize.py
canvas_markdown_quiz-0.3.0.dist-info/LICENSE
canvas_markdown_quiz-0.3.0.dist-info/METADATA
canvas_markdown_quiz-0.3.0.dist-info/WHEEL
canvas_markdown_quiz-0.3.0.dist-info/entry_points.txt
canvas_markdown_quiz-0.3.0.dist-info/top_level.txt
canvas_markdown_quiz-0.3.0.dist-info/RECORD
